edustaa/__init__.py
edustaa/__main__.py
edustaa/api.py
edustaa/cli.py
edustaa/css.py
edustaa/html.py
edustaa/js.py
edustaa/md.py
edustaa/pdf.py
edustaa/troff.py
edustaa-2023.6.24.dist-info/LICENSE
edustaa-2023.6.24.dist-info/METADATA
edustaa-2023.6.24.dist-info/WHEEL
edustaa-2023.6.24.dist-info/entry_points.txt
edustaa-2023.6.24.dist-info/top_level.txt
edustaa-2023.6.24.dist-info/RECORD
